Workbook

Sheet KPI Dashboard
A1: W04 KPI Framework — Fari, Senpai, and Sentinel Prime AI
A4: Three-platform KPI tracking framework
A5: Platform | B5: KPI area | C5: KPI | D5: Formula | E5: Public data / proxy | F5: Target range | G5: Reporting frequency | H5: TCO / business link
A6: Fari | B6: Deployment & adoption | C6: Active paid facilities | D6: Count of facilities with live deployment and paid status at period end | E6: InGen CRM and signed facility contracts; CMS facility counts for market context | F6: =TEXT('Target Inputs'!$C$7,"#,##0")&" active paid facilities by end of Year 3; at or above quarterly rollout plan" -> 74 active paid facilities by end of Year 3; at or above quarterly rollout plan | G6: Quarterly | H6: Tracks progress toward the W03 SOM
A7: Fari | B7: Operational performance | C7: Resident-session completion rate | D7: Completed resident sessions / scheduled resident sessions | E7: Device event logs and pilot schedules | F7: At least 90% after pilot stabilization | G7: Monthly | H7: Confirms that paid capacity is actually used
A8: Fari | B8: Energy efficiency | C8: kWh per completed resident session | D8: Metered charging kWh / completed resident sessions | E8: Smart-plug readings or onboard battery logs | F8: At or below the energy-per-session baseline from smart-plug and session logs in pilot Days 1–30; freeze after Day 30 | G8: Monthly | H8: Tracks energy cost per unit of use
A9: Fari | B9: Customer economics | C9: Cost per completed resident session | D9: (Annualized robot TCO + human support cost) / completed resident sessions | E9: Customer invoices, power use, support time, and current staff cost | F9: At or below the staff-assisted baseline from customer cost and support-time records in pilot Days 1–30; freeze after Day 30 | G9: Quarterly | H9: Direct customer unit-cost comparison
A10: Fari | B10: Business health | C10: Revenue per active facility | D10: Annualized recognized revenue / average active paid facilities | E10: Billing records and CRM deployment status | F10: ="$"&TEXT('Target Inputs'!$C$9,"#,##0")&"–$"&TEXT('Target Inputs'!$C$10,"#,##0")&" per facility-year" -> $13,500–$16,500 per facility-year | G10: Quarterly | H10: Uses the W03 modeled value per facility
A11: Senpai | B11: Deployment & adoption | C11: Active paid schools | D11: Count of schools with live deployment and paid status at period end | E11: InGen CRM and school contracts; NCES school counts for market context | F11: =TEXT('Target Inputs'!$C$11,"#,##0")&" active paid schools by end of Year 3; at or above quarterly rollout plan" -> 141 active paid schools by end of Year 3; at or above quarterly rollout plan | G11: Quarterly | H11: Tracks progress toward the W03 SOM
A12: Senpai | B12: Operational performance | C12: Student-session completion rate | D12: Completed student sessions / scheduled student sessions | E12: Device event logs and school schedules | F12: At least 90% after pilot stabilization | G12: Monthly | H12: Confirms that planned sessions are delivered
A13: Senpai | B13: Energy efficiency | C13: kWh per completed student session | D13: Metered charging kWh / completed student sessions | E13: Smart-plug readings or onboard battery logs | F13: At or below the energy-per-session baseline from smart-plug and session logs in pilot Days 1–30; freeze after Day 30 | G13: Monthly | H13: Tracks energy cost per unit of use
A14: Senpai | B14: Customer economics | C14: Cost per completed student session | D14: (Annualized robot TCO + staff support cost) / completed student sessions | E14: School invoices, power use, support time, and current staff cost | F14: At or below the staff-supported baseline from school cost and support-time records in pilot Days 1–30; freeze after Day 30 | G14: Quarterly | H14: Direct customer unit-cost comparison
A15: Senpai | B15: Business health | C15: Revenue per active school | D15: Annualized recognized revenue / average active paid schools | E15: Billing records and CRM deployment status | F15: ="$"&TEXT('Target Inputs'!$C$13,"#,##0")&"–$"&TEXT('Target Inputs'!$C$14,"#,##0")&" per school-year" -> $15,291–$18,689 per school-year | G15: Quarterly | H15: Uses the W03 modeled value per school
A16: Sentinel Prime AI | B16: Deployment & adoption | C16: Active paid deployments | D16: Count of live paid deployments at period end | E16: InGen CRM and customer contracts; BLS security employment for market context | F16: =TEXT('Target Inputs'!$C$27,"#,##0")&"–"&TEXT('Target Inputs'!$C$28,"#,##0")&" active paid deployments by end of Year 3 (base "&TEXT('Target Inputs'!$C$15,"#,##0")&")" -> 184–920 active paid deployments by end of Year 3 (base 276) | G16: Quarterly | H16: Tracks progress toward the W03 SOM
A17: Sentinel Prime AI | B17: Operational performance | C17: Monitoring availability | D17: Available monitored hours / scheduled monitored hours | E17: Platform uptime and downtime logs | F17: ="At least "&TEXT(1-'Target Inputs'!$C$16,"0%") -> At least 98% | G17: Monthly | H17: Matches the 2% downtime-backup assumption
A18: Sentinel Prime AI | B18: Energy efficiency | C18: kWh per monitored hour | D18: Metered electricity use / monitored hours | E18: Site meter or device telemetry | F18: ="At or below "&TEXT('Target Inputs'!$C$24,"0.000")&" kWh per monitored hour" -> At or below 0.125 kWh per monitored hour | G18: Monthly | H18: Uses the W03 3 kWh/day assumption
A19: Sentinel Prime AI | B19: Customer economics | C19: Five-year cost per monitored hour | D19: Five-year Sentinel TCO / five-year monitored hours | E19: TCO workbook, invoices, telemetry, and customer labor cost | F19: ="At or below $"&TEXT('Target Inputs'!$C$22,"0.00")&" per monitored hour; human baseline $"&TEXT('Target Inputs'!$C$23,"0.00") -> At or below $11.63 per monitored hour; human baseline $28.23 | G19: Quarterly | H19: Compares directly with human-security cost per hour
A20: Sentinel Prime AI | B20: Business health | C20: Recurring revenue per active deployment | D20: Annualized recurring revenue / average active paid deployments | E20: Billing records and CRM deployment status | F20: ="$"&TEXT('Target Inputs'!$C$25,"#,##0")&"–$"&TEXT('Target Inputs'!$C$26,"#,##0")&" per deployment-year" -> $11,250–$13,750 per deployment-year | G20: Quarterly | H20: Uses the W03 software / monitoring value

Sheet Target Inputs
A1: W04 KPI Framework — Target Inputs
A5: Platform | B5: Input | C5: Value | D5: Unit | E5: Type | F5: Source ID | G5: Note
A6: All | B6: Planning band around modeled unit value | C6: 0.1 | D6: % | E6: Analyst estimate | F6: — | G6: Used for revenue-per-unit target ranges
A7: Fari | B7: Year 3 SOM | C7: 74 | D7: facilities | E7: W03 output | F7: S01 | G7: W03 base case
A8: Fari | B8: Modeled value per facility | C8: 15000 | D8: USD/facility-year | E8: W03 input | F8: S01 | G8: W03 value-per-unit assumption
A9: Fari | B9: Lower revenue-per-facility target | C9: ='Target Inputs'!C8*(1-'Target Inputs'!C6) -> 13500 | D9: USD/facility-year | E9: Formula | F9: S01 | G9: Modeled value less 10%
A10: Fari | B10: Upper revenue-per-facility target | C10: ='Target Inputs'!C8*(1+'Target Inputs'!C6) -> 16500 | D10: USD/facility-year | E10: Formula | F10: S01 | G10: Modeled value plus 10%
A11: Senpai | B11: Year 3 SOM | C11: 141 | D11: schools | E11: W03 output | F11: S01 | G11: W03 base case
A12: Senpai | B12: Modeled value per school | C12: 16990 | D12: USD/school-year | E12: W03 input | F12: S01 | G12: W03 value-per-unit assumption
A13: Senpai | B13: Lower revenue-per-school target | C13: ='Target Inputs'!C12*(1-'Target Inputs'!C6) -> 15291 | D13: USD/school-year | E13: Formula | F13: S01 | G13: Modeled value less 10%
A14: Senpai | B14: Upper revenue-per-school target | C14: ='Target Inputs'!C12*(1+'Target Inputs'!C6) -> 18689 | D14: USD/school-year | E14: Formula | F14: S01 | G14: Modeled value plus 10%
A15: Sentinel Prime AI | B15: Year 3 SOM — Base | C15: 276 | D15: deployments | E15: W03 output | F15: S01 | G15: W03 0.03% base case
A16: Sentinel Prime AI | B16: Downtime backup rate | C16: 0.02 | D16: % scheduled hours | E16: W03 input | F16: S02 | G16: Availability target equals 1 minus downtime rate
A17: Sentinel Prime AI | B17: Daily electricity use | C17: 3 | D17: kWh/day | E17: W03 input | F17: S02 | G17: W03 base case
A18: Sentinel Prime AI | B18: Monitoring coverage | C18: 24 | D18: hours/day | E18: W03 input | F18: S02 | G18: Continuous monitoring post
A19: Sentinel Prime AI | B19: Five-year Sentinel TCO | C19: 509446.89 | D19: USD | E19: W03 output | F19: S02 | G19: W03 base case
A20: Sentinel Prime AI | B20: Five-year human-security TCO | C20: 1236433.5 | D20: USD | E20: W03 output | F20: S02 | G20: W03 base case
A21: Sentinel Prime AI | B21: Annual software / monitoring | C21: 12500 | D21: USD/deployment-year | E21: W03 input | F21: S02 | G21: Recurring revenue proxy
A22: Sentinel Prime AI | B22: Five-year cost per monitored hour | C22: ='Target Inputs'!C19/(5*365*'Target Inputs'!C18) -> 11.631208 | D22: USD/hour | E22: Formula | F22: S02 | G22: Sentinel TCO divided by five-year monitored hours
A23: Sentinel Prime AI | B23: Human cost per monitored hour | C23: ='Target Inputs'!C20/(5*365*'Target Inputs'!C18) -> 28.229076 | D23: USD/hour | E23: Formula | F23: S02 | G23: Human-security TCO divided by five-year monitored hours
A24: Sentinel Prime AI | B24: Energy per monitored hour | C24: ='Target Inputs'!C17/'Target Inputs'!C18 -> 0.125 | D24: kWh/hour | E24: Formula | F24: S02 | G24: Daily electricity divided by monitored hours
A25: Sentinel Prime AI | B25: Lower recurring-revenue target | C25: ='Target Inputs'!C21*(1-'Target Inputs'!C6) -> 11250 | D25: USD/deployment-year | E25: Formula | F25: S02 | G25: Annual software / monitoring less 10%
A26: Sentinel Prime AI | B26: Upper recurring-revenue target | C26: ='Target Inputs'!C21*(1+'Target Inputs'!C6) -> 13750 | D26: USD/deployment-year | E26: Formula | F26: S02 | G26: Annual software / monitoring plus 10%
A27: Sentinel Prime AI | B27: Year 3 SOM — Low | C27: 184 | D27: deployments | E27: W03 scenario | F27: S01 | G27: W03 0.02% low case
A28: Sentinel Prime AI | B28: Year 3 SOM — High | C28: 920 | D28: deployments | E28: W03 scenario | F28: S01 | G28: W03 0.10% high case

Sheet Checks
A1: W04 KPI Framework — Checks
A5: Check | B5: Actual | C5: Expected | D5: Difference | E5: Tolerance | F5: Status | G5: Notes
A6: Total KPI count | B6: =COUNTA('KPI Dashboard'!C6:C20) -> 15 | C6: 15 | D6: =B6-C6 -> 0 | E6: 0 | F6: =IF(D6=0,"PASS","FAIL") -> PASS | G6: Three platforms × five KPIs.
A7: Fari KPI count | B7: =COUNTIF('KPI Dashboard'!A6:A20,"Fari") -> 5 | C7: 5 | D7: =B7-C7 -> 0 | E7: 0 | F7: =IF(D7=0,"PASS","FAIL") -> PASS | G7: Fari has five KPI rows.
A8: Senpai KPI count | B8: =COUNTIF('KPI Dashboard'!A6:A20,"Senpai") -> 5 | C8: 5 | D8: =B8-C8 -> 0 | E8: 0 | F8: =IF(D8=0,"PASS","FAIL") -> PASS | G8: Senpai has five KPI rows.
A9: Sentinel Prime AI KPI count | B9: =COUNTIF('KPI Dashboard'!A6:A20,"Sentinel Prime AI") -> 5 | C9: 5 | D9: =B9-C9 -> 0 | E9: 0 | F9: =IF(D9=0,"PASS","FAIL") -> PASS | G9: Sentinel has five KPI rows.
A10: Required KPI fields completed | B10: =COUNTBLANK('KPI Dashboard'!A6:H20) -> 0 | C10: 0 | D10: =B10-C10 -> 0 | E10: 0 | F10: =IF(D10=0,"PASS","FAIL") -> PASS | G10: Platform, area, KPI, formula, proxy, target, frequency, and link are populated.
A11: Five KPI areas used for each platform | B11: =COUNTIF('KPI Dashboard'!B6:B20,"Deployment & adoption")+COUNTIF('KPI Dashboard'!B6:B20,"Operational performance")+COUNTIF('KPI Dashboard'!B6:B20,"Energy efficiency")+COUNTIF('KPI Dashboard'!B6:B20,"Customer economics")+COUNTIF('KPI Dashboard'!B6:B20,"Business health") -> 15 | C11: 15 | D11: =B11-C11 -> 0 | E11: 0 | F11: =IF(D11=0,"PASS","FAIL") -> PASS | G11: Each platform covers deployment, operations, energy, customer economics, and business health.
A12: Target-input types completed | B12: =COUNTBLANK('Target Inputs'!E6:E28) -> 0 | C12: 0 | D12: =B12-C12 -> 0 | E12: 0 | F12: =IF(D12=0,"PASS","FAIL") -> PASS | G12: Every Target Inputs row has a Type classification.
A14: MODEL STATUS | F14: =IF(COUNTIF(F6:F12,"FAIL")=0,"PASS","FAIL") -> PASS

Sheet Sources
A1: W04 KPI Framework — Sources
A5: Source ID | B5: Use | C5: Value / Measure | D5: Period | E5: Source | F5: URL | G5: Notes
A6: S01 | B6: SOM and modeled value-per-unit targets | C6: Fari 74 / $15,000; Senpai 141 / $16,990; Sentinel 184–920 (base 276) | D6: Week 3 | E6: W03_TAM_SAM_SOM_Model.xlsx | G6: Provides Fari and Senpai base targets plus the Sentinel low, base, and high deployment cases.
A7: S02 | B7: Sentinel operating and customer-economics targets | C7: 2% downtime; 3 kWh/day; $509,447 five-year TCO | D7: Week 3 | E7: W03_TCO_Analysis.xlsx | G7: Provides availability, energy, cost-per-hour, and recurring software inputs.
A8: S03 | B8: Fari market context | C8: CMS-certified nursing facilities | D8: Current data page | E8: CMS Provider Data — Nursing Homes | F8: https://data.cms.gov/provider-data/topics/nursing-homes | G8: Public market proxy; operating KPIs require pilot logs.
A9: S04 | B9: Senpai market context | C9: Public schools and enrollment | D9: Current data page | E9: NCES Common Core of Data | F9: https://nces.ed.gov/ccd/files.asp | G9: Public market proxy; operating KPIs require school and device logs.
A10: S05 | B10: Sentinel market and labor context | C10: Security guard employment and wages | D10: May 2025 | E10: BLS OEWS National | F10: https://www.bls.gov/oes/tables.htm | G10: Public labor proxy for customer-economics comparisons.
A11: S06 | B11: Required KPI categories and fields | C11: Three platforms × five KPIs | D11: Week 4 | E11: Internship plan | G11: Defines the KPI framework scope, formulas, targets, proxies, and frequency.
