Workbook

Sheet Summary
A1: W04 Sentinel Prime AI Cost-Benefit Analysis
A4: Base-case result
A5: Metric | B5: Value | C5: Basis | D5: Interpretation
A6: Initial investment | B6: =Assumptions!C31 -> 98125 | C6: Year 0 | D6: Initial deployment cost is counted once.
A7: Discount rate | B7: =Assumptions!C10 -> 0.0775 | C7: 4.75% Treasury + 3.00% premium | D7: Treasury date: 2026-07-31.
A8: NPV | B8: ='Cash Flow'!B29 -> 561510.68 | C8: Selected-horizon discounted cash flow | D8: Positive value after the initial investment.
A9: IRR | B9: ='Cash Flow'!B30 -> 1.5869643 | C9: IRR() on net cash flow | D9: Savings are high relative to the initial outlay.
A10: Payback year | B10: ='Cash Flow'!B31 -> Year 1 | C10: Cumulative cash flow | D10: Cumulative cash flow turns positive in Year 1.
A11: Approximate payback | B11: ='Cash Flow'!B32 -> 7.634388 | C11: Linear estimate within Year 1 | D11: The initial investment is recovered in about 7.6 months.
A14: Required sensitivity results
A15: Scenario | B15: NPV | C15: Change vs. base | D15: IRR | E15: Payback year | F15: Approx. payback
A16: =Sensitivity!A6 -> Base | B16: =Sensitivity!E6 -> 561510.68 | C16: =Sensitivity!F6 -> 0 | D16: =Sensitivity!G6 -> 1.5869643 | E16: =Sensitivity!H6 -> Year 1 | F16: =Sensitivity!I6 -> 7.634388
A17: =Sensitivity!A7 -> Hardware cost +20% | B17: =Sensitivity!E7 -> 540090.77 | C17: =Sensitivity!F7 -> -21419.909 | D17: =Sensitivity!G7 -> 1.3129426 | E17: =Sensitivity!H7 -> Year 1 | F17: =Sensitivity!I7 -> 9.1985401
A18: =Sensitivity!A8 -> Useful life reduced to 3 years | B18: =Sensitivity!E8 -> 317646.83 | C18: =Sensitivity!F8 -> -243863.85 | D18: =Sensitivity!G8 -> 1.4975912 | E18: =Sensitivity!H8 -> Year 1 | F18: =Sensitivity!I8 -> 7.634388
A21: Main result
A22: Largest NPV impact | B22: =Sensitivity!B19 -> Useful life reduced to 3 years
A23: Business meaning | B23: One modeled deployment already has positive NPV and reaches payback in Year 1, so this customer-side model does not imply a minimum contract-size requirement.

Sheet Assumptions
A1: W04 Sentinel Prime AI Cost-Benefit Analysis — Assumptions
A5: Category | B5: Input | C5: Value | D5: Unit | E5: Type | F5: Source ID | G5: Derivation / Note
A6: General | B6: Model horizon | C6: 5 | D6: years | E6: Required assumption | F6: S06 | G6: Controls operating cash flows and end-of-life value; default is five years
A7: General | B7: Annual cost escalation | C7: 0.03 | D7: %/year | E7: W03 input | F7: S01 | G7: Applied to recurring costs
A8: Discount rate | B8: 10-year Treasury yield | C8: 0.0475 | D8: % | E8: Public source | F8: S02 | G8: U.S. Treasury daily par yield curve, 2026-07-31
A9: Discount rate | B9: Risk premium | C9: 0.03 | D9: % | E9: Required assumption | F9: S06 | G9: Added to the 10-year Treasury yield
A10: Discount rate | B10: Applied discount rate | C10: =Assumptions!C8+Assumptions!C9 -> 0.0775 | D10: % | E10: Formula | F10: S02/S06 | G10: Treasury yield plus risk premium
A12: Initial deployment | B12: Hardware / system cost | C12: 62500 | D12: USD | E12: W03 input | F12: S01/S05 | G12: Midpoint of the Week 1 Tier 3 estimate
A13: Initial deployment | B13: Shipping | C13: 0.05 | D13: % hardware | E13: W03 input | F13: S01 | G13: Percentage of hardware cost
A14: Initial deployment | B14: Additional sensors / payload | C14: 0.16 | D14: % hardware | E14: W03 input | F14: S01 | G14: Percentage of hardware cost
A15: Initial deployment | B15: Site preparation | C15: 0.08 | D15: % hardware | E15: W03 input | F15: S01 | G15: Percentage of hardware cost
A16: Initial deployment | B16: Integration | C16: 0.2 | D16: % hardware | E16: W03 input | F16: S01 | G16: Percentage of hardware cost
A17: Initial deployment | B17: Training | C17: 0.08 | D17: % hardware | E17: W03 input | F17: S01 | G17: Percentage of hardware cost
A18: Recurring | B18: Software / monitoring | C18: 12500 | D18: USD/year | E18: W03 input | F18: S01 | G18: W03 set this amount at 20% of base hardware; this sensitivity holds the contract-priced software amount fixed
A19: Recurring | B19: Daily electricity use | C19: 3 | D19: kWh/day | E19: W03 input | F19: S01 | G19: 24/7 sensor and edge-compute estimate
A20: Recurring | B20: Operating days | C20: 365 | D20: days/year | E20: Required assumption | F20: S01 | G20: Continuous operation
A21: Recurring | B21: Commercial electricity price | C21: 0.1341 | D21: USD/kWh | E21: Public source | F21: S04 | G21: 2025 U.S. commercial average
A22: Recurring | B22: Maintenance rate | C22: 0.05 | D22: % hardware/year | E22: Required assumption | F22: S01 | G22: Applied to hardware cost
A23: Labor | B23: Security-guard mean hourly wage | C23: 20.42 | D23: USD/hour | E23: Public source | F23: S03 | G23: BLS OEWS H_MEAN for OCC 33-9032
A24: Labor | B24: ECEC benefit load factor | C24: 1.3019284 | D24: x wage | E24: W03 formula | F24: S03 | G24: W03: $23.63 total compensation divided by $18.15 wages and salaries
A25: Labor | B25: Loaded security-guard cost | C25: =Assumptions!C23*Assumptions!C24 -> 26.585377 | D25: USD/hour | E25: Formula | F25: S03 | G25: Mean hourly wage multiplied by the ECEC benefit load factor
A26: Labor | B26: Human-security coverage | C26: 24 | D26: hours/day | E26: W03 input | F26: S01 | G26: One continuous monitoring post
A27: Labor | B27: Human oversight share | C27: 0.25 | D27: % guard hours | E27: W03 input | F27: S01 | G27: Human-in-the-loop review and response
A28: Labor | B28: Downtime backup rate | C28: 0.02 | D28: % guard hours | E28: W03 input | F28: S01 | G28: Human backup while unavailable
A29: Recovery | B29: End-of-life value | C29: 0.1 | D29: % hardware | E29: W03 input | F29: S01 | G29: Recovered at the end of the selected useful life; the same 10% basis is used in the three-year case
A30: Reference | B30: W03 five-year nominal savings | C30: 726986.63 | D30: USD | E30: W03 output | F30: S01 | G30: Used only for reconciliation
A31: Calculated | B31: Initial investment | C31: =Assumptions!C12*(1+SUM(Assumptions!C13:C17)) -> 98125 | D31: USD | E31: Formula | F31: S01 | G31: Hardware plus shipping, payload, site work, integration, and training

Sheet Cash Flow
A1: Sentinel Prime AI — Five-Year Discounted Cash Flow
A4: Cash flow item | B4: 0 | C4: 1 | D4: 2 | E4: 3 | F4: 4 | G4: 5
A5: Initial investment
A6: Hardware / system | B6: =-IF(B$4=0,Assumptions!$C$12,0) -> -62500 | C6: =-IF(C$4=0,Assumptions!$C$12,0) -> 0 | D6: =-IF(D$4=0,Assumptions!$C$12,0) -> 0 | E6: =-IF(E$4=0,Assumptions!$C$12,0) -> 0 | F6: =-IF(F$4=0,Assumptions!$C$12,0) -> 0 | G6: =-IF(G$4=0,Assumptions!$C$12,0) -> 0
A7: Shipping | B7: =-IF(B$4=0,Assumptions!$C$12*Assumptions!$C$13,0) -> -3125 | C7: =-IF(C$4=0,Assumptions!$C$12*Assumptions!$C$13,0) -> 0 | D7: =-IF(D$4=0,Assumptions!$C$12*Assumptions!$C$13,0) -> 0 | E7: =-IF(E$4=0,Assumptions!$C$12*Assumptions!$C$13,0) -> 0 | F7: =-IF(F$4=0,Assumptions!$C$12*Assumptions!$C$13,0) -> 0 | G7: =-IF(G$4=0,Assumptions!$C$12*Assumptions!$C$13,0) -> 0
A8: Additional sensors / payload | B8: =-IF(B$4=0,Assumptions!$C$12*Assumptions!$C$14,0) -> -10000 | C8: =-IF(C$4=0,Assumptions!$C$12*Assumptions!$C$14,0) -> 0 | D8: =-IF(D$4=0,Assumptions!$C$12*Assumptions!$C$14,0) -> 0 | E8: =-IF(E$4=0,Assumptions!$C$12*Assumptions!$C$14,0) -> 0 | F8: =-IF(F$4=0,Assumptions!$C$12*Assumptions!$C$14,0) -> 0 | G8: =-IF(G$4=0,Assumptions!$C$12*Assumptions!$C$14,0) -> 0
A9: Site preparation | B9: =-IF(B$4=0,Assumptions!$C$12*Assumptions!$C$15,0) -> -5000 | C9: =-IF(C$4=0,Assumptions!$C$12*Assumptions!$C$15,0) -> 0 | D9: =-IF(D$4=0,Assumptions!$C$12*Assumptions!$C$15,0) -> 0 | E9: =-IF(E$4=0,Assumptions!$C$12*Assumptions!$C$15,0) -> 0 | F9: =-IF(F$4=0,Assumptions!$C$12*Assumptions!$C$15,0) -> 0 | G9: =-IF(G$4=0,Assumptions!$C$12*Assumptions!$C$15,0) -> 0
A10: Integration | B10: =-IF(B$4=0,Assumptions!$C$12*Assumptions!$C$16,0) -> -12500 | C10: =-IF(C$4=0,Assumptions!$C$12*Assumptions!$C$16,0) -> 0 | D10: =-IF(D$4=0,Assumptions!$C$12*Assumptions!$C$16,0) -> 0 | E10: =-IF(E$4=0,Assumptions!$C$12*Assumptions!$C$16,0) -> 0 | F10: =-IF(F$4=0,Assumptions!$C$12*Assumptions!$C$16,0) -> 0 | G10: =-IF(G$4=0,Assumptions!$C$12*Assumptions!$C$16,0) -> 0
A11: Training | B11: =-IF(B$4=0,Assumptions!$C$12*Assumptions!$C$17,0) -> -5000 | C11: =-IF(C$4=0,Assumptions!$C$12*Assumptions!$C$17,0) -> 0 | D11: =-IF(D$4=0,Assumptions!$C$12*Assumptions!$C$17,0) -> 0 | E11: =-IF(E$4=0,Assumptions!$C$12*Assumptions!$C$17,0) -> 0 | F11: =-IF(F$4=0,Assumptions!$C$12*Assumptions!$C$17,0) -> 0 | G11: =-IF(G$4=0,Assumptions!$C$12*Assumptions!$C$17,0) -> 0
A12: Total initial investment | B12: =SUM(B6:B11) -> -98125 | C12: =SUM(C6:C11) -> 0 | D12: =SUM(D6:D11) -> 0 | E12: =SUM(E6:E11) -> 0 | F12: =SUM(F6:F11) -> 0 | G12: =SUM(G6:G11) -> 0
A14: Annual savings and operating cash flow
A15: Human-security cost avoided | B15: =IF(OR(B$4=0,B$4>Assumptions!$C$6),0,Assumptions!$C$25*Assumptions!$C$26*Assumptions!$C$20*(1+Assumptions!$C$7)^(B$4-1)) -> 0 | C15: =IF(OR(C$4=0,C$4>Assumptions!$C$6),0,Assumptions!$C$25*Assumptions!$C$26*Assumptions!$C$20*(1+Assumptions!$C$7)^(C$4-1)) -> 232887.91 | D15: =IF(OR(D$4=0,D$4>Assumptions!$C$6),0,Assumptions!$C$25*Assumptions!$C$26*Assumptions!$C$20*(1+Assumptions!$C$7)^(D$4-1)) -> 239874.54 | E15: =IF(OR(E$4=0,E$4>Assumptions!$C$6),0,Assumptions!$C$25*Assumptions!$C$26*Assumptions!$C$20*(1+Assumptions!$C$7)^(E$4-1)) -> 247070.78 | F15: =IF(OR(F$4=0,F$4>Assumptions!$C$6),0,Assumptions!$C$25*Assumptions!$C$26*Assumptions!$C$20*(1+Assumptions!$C$7)^(F$4-1)) -> 254482.9 | G15: =IF(OR(G$4=0,G$4>Assumptions!$C$6),0,Assumptions!$C$25*Assumptions!$C$26*Assumptions!$C$20*(1+Assumptions!$C$7)^(G$4-1)) -> 262117.39
A16: Software / monitoring | B16: =IF(OR(B$4=0,B$4>Assumptions!$C$6),0,-Assumptions!$C$18*(1+Assumptions!$C$7)^(B$4-1)) -> 0 | C16: =IF(OR(C$4=0,C$4>Assumptions!$C$6),0,-Assumptions!$C$18*(1+Assumptions!$C$7)^(C$4-1)) -> -12500 | D16: =IF(OR(D$4=0,D$4>Assumptions!$C$6),0,-Assumptions!$C$18*(1+Assumptions!$C$7)^(D$4-1)) -> -12875 | E16: =IF(OR(E$4=0,E$4>Assumptions!$C$6),0,-Assumptions!$C$18*(1+Assumptions!$C$7)^(E$4-1)) -> -13261.25 | F16: =IF(OR(F$4=0,F$4>Assumptions!$C$6),0,-Assumptions!$C$18*(1+Assumptions!$C$7)^(F$4-1)) -> -13659.087 | G16: =IF(OR(G$4=0,G$4>Assumptions!$C$6),0,-Assumptions!$C$18*(1+Assumptions!$C$7)^(G$4-1)) -> -14068.86
A17: Electricity | B17: =IF(OR(B$4=0,B$4>Assumptions!$C$6),0,-Assumptions!$C$19*Assumptions!$C$20*Assumptions!$C$21*(1+Assumptions!$C$7)^(B$4-1)) -> 0 | C17: =IF(OR(C$4=0,C$4>Assumptions!$C$6),0,-Assumptions!$C$19*Assumptions!$C$20*Assumptions!$C$21*(1+Assumptions!$C$7)^(C$4-1)) -> -146.8395 | D17: =IF(OR(D$4=0,D$4>Assumptions!$C$6),0,-Assumptions!$C$19*Assumptions!$C$20*Assumptions!$C$21*(1+Assumptions!$C$7)^(D$4-1)) -> -151.24469 | E17: =IF(OR(E$4=0,E$4>Assumptions!$C$6),0,-Assumptions!$C$19*Assumptions!$C$20*Assumptions!$C$21*(1+Assumptions!$C$7)^(E$4-1)) -> -155.78203 | F17: =IF(OR(F$4=0,F$4>Assumptions!$C$6),0,-Assumptions!$C$19*Assumptions!$C$20*Assumptions!$C$21*(1+Assumptions!$C$7)^(F$4-1)) -> -160.45549 | G17: =IF(OR(G$4=0,G$4>Assumptions!$C$6),0,-Assumptions!$C$19*Assumptions!$C$20*Assumptions!$C$21*(1+Assumptions!$C$7)^(G$4-1)) -> -165.26915
A18: Maintenance | B18: =IF(OR(B$4=0,B$4>Assumptions!$C$6),0,-Assumptions!$C$12*Assumptions!$C$22*(1+Assumptions!$C$7)^(B$4-1)) -> 0 | C18: =IF(OR(C$4=0,C$4>Assumptions!$C$6),0,-Assumptions!$C$12*Assumptions!$C$22*(1+Assumptions!$C$7)^(C$4-1)) -> -3125 | D18: =IF(OR(D$4=0,D$4>Assumptions!$C$6),0,-Assumptions!$C$12*Assumptions!$C$22*(1+Assumptions!$C$7)^(D$4-1)) -> -3218.75 | E18: =IF(OR(E$4=0,E$4>Assumptions!$C$6),0,-Assumptions!$C$12*Assumptions!$C$22*(1+Assumptions!$C$7)^(E$4-1)) -> -3315.3125 | F18: =IF(OR(F$4=0,F$4>Assumptions!$C$6),0,-Assumptions!$C$12*Assumptions!$C$22*(1+Assumptions!$C$7)^(F$4-1)) -> -3414.7719 | G18: =IF(OR(G$4=0,G$4>Assumptions!$C$6),0,-Assumptions!$C$12*Assumptions!$C$22*(1+Assumptions!$C$7)^(G$4-1)) -> -3517.215
A19: Human oversight | B19: =IF(OR(B$4=0,B$4>Assumptions!$C$6),0,-Assumptions!$C$25*Assumptions!$C$26*Assumptions!$C$20*Assumptions!$C$27*(1+Assumptions!$C$7)^(B$4-1)) -> 0 | C19: =IF(OR(C$4=0,C$4>Assumptions!$C$6),0,-Assumptions!$C$25*Assumptions!$C$26*Assumptions!$C$20*Assumptions!$C$27*(1+Assumptions!$C$7)^(C$4-1)) -> -58221.977 | D19: =IF(OR(D$4=0,D$4>Assumptions!$C$6),0,-Assumptions!$C$25*Assumptions!$C$26*Assumptions!$C$20*Assumptions!$C$27*(1+Assumptions!$C$7)^(D$4-1)) -> -59968.636 | E19: =IF(OR(E$4=0,E$4>Assumptions!$C$6),0,-Assumptions!$C$25*Assumptions!$C$26*Assumptions!$C$20*Assumptions!$C$27*(1+Assumptions!$C$7)^(E$4-1)) -> -61767.695 | F19: =IF(OR(F$4=0,F$4>Assumptions!$C$6),0,-Assumptions!$C$25*Assumptions!$C$26*Assumptions!$C$20*Assumptions!$C$27*(1+Assumptions!$C$7)^(F$4-1)) -> -63620.726 | G19: =IF(OR(G$4=0,G$4>Assumptions!$C$6),0,-Assumptions!$C$25*Assumptions!$C$26*Assumptions!$C$20*Assumptions!$C$27*(1+Assumptions!$C$7)^(G$4-1)) -> -65529.348
A20: Downtime backup labor | B20: =IF(OR(B$4=0,B$4>Assumptions!$C$6),0,-Assumptions!$C$25*Assumptions!$C$26*Assumptions!$C$20*Assumptions!$C$28*(1+Assumptions!$C$7)^(B$4-1)) -> 0 | C20: =IF(OR(C$4=0,C$4>Assumptions!$C$6),0,-Assumptions!$C$25*Assumptions!$C$26*Assumptions!$C$20*Assumptions!$C$28*(1+Assumptions!$C$7)^(C$4-1)) -> -4657.7581 | D20: =IF(OR(D$4=0,D$4>Assumptions!$C$6),0,-Assumptions!$C$25*Assumptions!$C$26*Assumptions!$C$20*Assumptions!$C$28*(1+Assumptions!$C$7)^(D$4-1)) -> -4797.4909 | E20: =IF(OR(E$4=0,E$4>Assumptions!$C$6),0,-Assumptions!$C$25*Assumptions!$C$26*Assumptions!$C$20*Assumptions!$C$28*(1+Assumptions!$C$7)^(E$4-1)) -> -4941.4156 | F20: =IF(OR(F$4=0,F$4>Assumptions!$C$6),0,-Assumptions!$C$25*Assumptions!$C$26*Assumptions!$C$20*Assumptions!$C$28*(1+Assumptions!$C$7)^(F$4-1)) -> -5089.6581 | G20: =IF(OR(G$4=0,G$4>Assumptions!$C$6),0,-Assumptions!$C$25*Assumptions!$C$26*Assumptions!$C$20*Assumptions!$C$28*(1+Assumptions!$C$7)^(G$4-1)) -> -5242.3478
A21: End-of-life value recovered | B21: =IF(B$4=Assumptions!$C$6,Assumptions!$C$12*Assumptions!$C$29,0) -> 0 | C21: =IF(C$4=Assumptions!$C$6,Assumptions!$C$12*Assumptions!$C$29,0) -> 0 | D21: =IF(D$4=Assumptions!$C$6,Assumptions!$C$12*Assumptions!$C$29,0) -> 0 | E21: =IF(E$4=Assumptions!$C$6,Assumptions!$C$12*Assumptions!$C$29,0) -> 0 | F21: =IF(F$4=Assumptions!$C$6,Assumptions!$C$12*Assumptions!$C$29,0) -> 0 | G21: =IF(G$4=Assumptions!$C$6,Assumptions!$C$12*Assumptions!$C$29,0) -> 6250
A22: Net cash flow | B22: =SUM(B6:B11)+SUM(B15:B21) -> -98125 | C22: =SUM(C6:C11)+SUM(C15:C21) -> 154236.33 | D22: =SUM(D6:D11)+SUM(D15:D21) -> 158863.42 | E22: =SUM(E6:E11)+SUM(E15:E21) -> 163629.32 | F22: =SUM(F6:F11)+SUM(F15:F21) -> 168538.2 | G22: =SUM(G6:G11)+SUM(G15:G21) -> 179844.35
A23: Discount factor | B23: =1/(1+Assumptions!$C$10)^B$4 -> 1 | C23: =1/(1+Assumptions!$C$10)^C$4 -> 0.92807425 | D23: =1/(1+Assumptions!$C$10)^D$4 -> 0.86132181 | E23: =1/(1+Assumptions!$C$10)^E$4 -> 0.79937059 | F23: =1/(1+Assumptions!$C$10)^F$4 -> 0.74187525 | G23: =1/(1+Assumptions!$C$10)^G$4 -> 0.68851532
A24: Discounted cash flow | B24: =B22*B23 -> -98125 | C24: =C22*C23 -> 143142.77 | D24: =D22*D23 -> 136832.53 | E24: =E22*E23 -> 130800.47 | F24: =F22*F23 -> 125034.32 | G24: =G22*G23 -> 123825.59
A25: Cumulative net cash flow | B25: =B22 -> -98125 | C25: =B25+C22 -> 56111.332 | D25: =C25+D22 -> 214974.75 | E25: =D25+E22 -> 378604.08 | F25: =E25+F22 -> 547142.28 | G25: =F25+G22 -> 726986.63
A26: Cumulative discounted cash flow | B26: =B24 -> -98125 | C26: =B26+C24 -> 45017.767 | D26: =C26+D24 -> 181850.3 | E26: =D26+E24 -> 312650.77 | F26: =E26+F24 -> 437685.09 | G26: =F26+G24 -> 561510.68
A28: Financial outputs
A29: NPV | B29: =NPV(Assumptions!$C$10,C22:G22)+B22 -> 561510.68 | C29: Present value of Year 1–5 savings less the Year 0 investment
A30: IRR | B30: =IRR(B22:G22) -> 1.5869643 | C30: Excel IRR() on Year 0–5 net cash flow
A31: Payback year | B31: =IF(C25>=0,"Year 1",IF(D25>=0,"Year 2",IF(E25>=0,"Year 3",IF(F25>=0,"Year 4",IF(G25>=0,"Year 5","Beyond 5 years"))))) -> Year 1 | C31: First year with non-negative cumulative cash flow
A32: Approximate payback | B32: =IF(C25>=0,ABS(B22)/C22*12,IF(D25>=0,12+ABS(C25)/D22*12,IF(E25>=0,24+ABS(D25)/E22*12,IF(F25>=0,36+ABS(E25)/F22*12,IF(G25>=0,48+ABS(F25)/G22*12,0))))) -> 7.634388 | C32: Linear estimate within the payback year

Sheet Sensitivity
A1: Sentinel Prime AI — Required Sensitivity Analysis
A4: Scenario summary
A5: Scenario | B5: Hardware multiplier | C5: Useful life | D5: Initial investment | E5: NPV | F5: Change vs. base | G5: IRR | H5: Payback year | I5: Approx. payback | J5: Interpretation
A6: Base | B6: 1 | C6: =Assumptions!$C$6 -> 5 | D6: =ABS(B13) -> 98125 | E6: =NPV(Assumptions!$C$10,C13:G13)+B13 -> 561510.68 | F6: =E6-$E$6 -> 0 | G6: =IRR(B13:G13) -> 1.5869643 | H6: =IF(SUM(B13:C13)>=0,"Year 1",IF(SUM(B13:D13)>=0,"Year 2",IF(SUM(B13:E13)>=0,"Year 3",IF(SUM(B13:F13)>=0,"Year 4",IF(SUM(B13:G13)>=0,"Year 5","Beyond 5 years"))))) -> Year 1 | I6: =IF(SUM(B13:C13)>=0,ABS(B13)/C13*12,IF(SUM(B13:D13)>=0,12+ABS(SUM(B13:C13))/D13*12,IF(SUM(B13:E13)>=0,24+ABS(SUM(B13:D13))/E13*12,IF(SUM(B13:F13)>=0,36+ABS(SUM(B13:E13))/F13*12,IF(SUM(B13:G13)>=0,48+ABS(SUM(B13:F13))/G13*12,0))))) -> 7.634388 | J6: Base case at the selected model horizon
A7: Hardware cost +20% | B7: 1.2 | C7: =$C$6 -> 5 | D7: =ABS(B14) -> 117750 | E7: =NPV(Assumptions!$C$10,C14:G14)+B14 -> 540090.77 | F7: =E7-$E$6 -> -21419.909 | G7: =IRR(B14:G14) -> 1.3129426 | H7: =IF(SUM(B14:C14)>=0,"Year 1",IF(SUM(B14:D14)>=0,"Year 2",IF(SUM(B14:E14)>=0,"Year 3",IF(SUM(B14:F14)>=0,"Year 4",IF(SUM(B14:G14)>=0,"Year 5","Beyond 5 years"))))) -> Year 1 | I7: =IF(SUM(B14:C14)>=0,ABS(B14)/C14*12,IF(SUM(B14:D14)>=0,12+ABS(SUM(B14:C14))/D14*12,IF(SUM(B14:E14)>=0,24+ABS(SUM(B14:D14))/E14*12,IF(SUM(B14:F14)>=0,36+ABS(SUM(B14:E14))/F14*12,IF(SUM(B14:G14)>=0,48+ABS(SUM(B14:F14))/G14*12,0))))) -> 9.1985401 | J7: Hardware-linked costs change; W03 set software at 20% of base hardware, but this case holds the contract price fixed
A8: Useful life reduced to 3 years | B8: 1 | C8: 3 | D8: =ABS(B15) -> 98125 | E8: =NPV(Assumptions!$C$10,C15:G15)+B15 -> 317646.83 | F8: =E8-$E$6 -> -243863.85 | G8: =IRR(B15:G15) -> 1.4975912 | H8: =IF(SUM(B15:C15)>=0,"Year 1",IF(SUM(B15:D15)>=0,"Year 2",IF(SUM(B15:E15)>=0,"Year 3",IF(SUM(B15:F15)>=0,"Year 4",IF(SUM(B15:G15)>=0,"Year 5","Beyond 5 years"))))) -> Year 1 | I8: =IF(SUM(B15:C15)>=0,ABS(B15)/C15*12,IF(SUM(B15:D15)>=0,12+ABS(SUM(B15:C15))/D15*12,IF(SUM(B15:E15)>=0,24+ABS(SUM(B15:D15))/E15*12,IF(SUM(B15:F15)>=0,36+ABS(SUM(B15:E15))/F15*12,IF(SUM(B15:G15)>=0,48+ABS(SUM(B15:F15))/G15*12,0))))) -> 7.634388 | J8: Year 4–5 cash flows are removed; residual value moves to Year 3 and remains 10% at end of useful life
A11: Net cash flow by scenario
A12: Scenario | B12: 0 | C12: 1 | D12: 2 | E12: 3 | F12: 4 | G12: 5
A13: =A6 -> Base | B13: =IF(B$12=0,-Assumptions!$C$12*$B6*(1+SUM(Assumptions!$C$13:$C$17)),IF(B$12>$C6,0,(Assumptions!$C$25*Assumptions!$C$26*Assumptions!$C$20-Assumptions!$C$18-Assumptions!$C$19*Assumptions!$C$20*Assumptions!$C$21-Assumptions!$C$12*$B6*Assumptions!$C$22-Assumptions!$C$25*Assumptions!$C$26*Assumptions!$C$20*Assumptions!$C$27-Assumptions!$C$25*Assumptions!$C$26*Assumptions!$C$20*Assumptions!$C$28)*(1+Assumptions!$C$7)^(B$12-1)+IF(B$12=$C6,Assumptions!$C$12*$B6*Assumptions!$C$29,0))) -> -98125 | C13: =IF(C$12=0,-Assumptions!$C$12*$B6*(1+SUM(Assumptions!$C$13:$C$17)),IF(C$12>$C6,0,(Assumptions!$C$25*Assumptions!$C$26*Assumptions!$C$20-Assumptions!$C$18-Assumptions!$C$19*Assumptions!$C$20*Assumptions!$C$21-Assumptions!$C$12*$B6*Assumptions!$C$22-Assumptions!$C$25*Assumptions!$C$26*Assumptions!$C$20*Assumptions!$C$27-Assumptions!$C$25*Assumptions!$C$26*Assumptions!$C$20*Assumptions!$C$28)*(1+Assumptions!$C$7)^(C$12-1)+IF(C$12=$C6,Assumptions!$C$12*$B6*Assumptions!$C$29,0))) -> 154236.33 | D13: =IF(D$12=0,-Assumptions!$C$12*$B6*(1+SUM(Assumptions!$C$13:$C$17)),IF(D$12>$C6,0,(Assumptions!$C$25*Assumptions!$C$26*Assumptions!$C$20-Assumptions!$C$18-Assumptions!$C$19*Assumptions!$C$20*Assumptions!$C$21-Assumptions!$C$12*$B6*Assumptions!$C$22-Assumptions!$C$25*Assumptions!$C$26*Assumptions!$C$20*Assumptions!$C$27-Assumptions!$C$25*Assumptions!$C$26*Assumptions!$C$20*Assumptions!$C$28)*(1+Assumptions!$C$7)^(D$12-1)+IF(D$12=$C6,Assumptions!$C$12*$B6*Assumptions!$C$29,0))) -> 158863.42 | E13: =IF(E$12=0,-Assumptions!$C$12*$B6*(1+SUM(Assumptions!$C$13:$C$17)),IF(E$12>$C6,0,(Assumptions!$C$25*Assumptions!$C$26*Assumptions!$C$20-Assumptions!$C$18-Assumptions!$C$19*Assumptions!$C$20*Assumptions!$C$21-Assumptions!$C$12*$B6*Assumptions!$C$22-Assumptions!$C$25*Assumptions!$C$26*Assumptions!$C$20*Assumptions!$C$27-Assumptions!$C$25*Assumptions!$C$26*Assumptions!$C$20*Assumptions!$C$28)*(1+Assumptions!$C$7)^(E$12-1)+IF(E$12=$C6,Assumptions!$C$12*$B6*Assumptions!$C$29,0))) -> 163629.32 | F13: =IF(F$12=0,-Assumptions!$C$12*$B6*(1+SUM(Assumptions!$C$13:$C$17)),IF(F$12>$C6,0,(Assumptions!$C$25*Assumptions!$C$26*Assumptions!$C$20-Assumptions!$C$18-Assumptions!$C$19*Assumptions!$C$20*Assumptions!$C$21-Assumptions!$C$12*$B6*Assumptions!$C$22-Assumptions!$C$25*Assumptions!$C$26*Assumptions!$C$20*Assumptions!$C$27-Assumptions!$C$25*Assumptions!$C$26*Assumptions!$C$20*Assumptions!$C$28)*(1+Assumptions!$C$7)^(F$12-1)+IF(F$12=$C6,Assumptions!$C$12*$B6*Assumptions!$C$29,0))) -> 168538.2 | G13: =IF(G$12=0,-Assumptions!$C$12*$B6*(1+SUM(Assumptions!$C$13:$C$17)),IF(G$12>$C6,0,(Assumptions!$C$25*Assumptions!$C$26*Assumptions!$C$20-Assumptions!$C$18-Assumptions!$C$19*Assumptions!$C$20*Assumptions!$C$21-Assumptions!$C$12*$B6*Assumptions!$C$22-Assumptions!$C$25*Assumptions!$C$26*Assumptions!$C$20*Assumptions!$C$27-Assumptions!$C$25*Assumptions!$C$26*Assumptions!$C$20*Assumptions!$C$28)*(1+Assumptions!$C$7)^(G$12-1)+IF(G$12=$C6,Assumptions!$C$12*$B6*Assumptions!$C$29,0))) -> 179844.35
A14: =A7 -> Hardware cost +20% | B14: =IF(B$12=0,-Assumptions!$C$12*$B7*(1+SUM(Assumptions!$C$13:$C$17)),IF(B$12>$C7,0,(Assumptions!$C$25*Assumptions!$C$26*Assumptions!$C$20-Assumptions!$C$18-Assumptions!$C$19*Assumptions!$C$20*Assumptions!$C$21-Assumptions!$C$12*$B7*Assumptions!$C$22-Assumptions!$C$25*Assumptions!$C$26*Assumptions!$C$20*Assumptions!$C$27-Assumptions!$C$25*Assumptions!$C$26*Assumptions!$C$20*Assumptions!$C$28)*(1+Assumptions!$C$7)^(B$12-1)+IF(B$12=$C7,Assumptions!$C$12*$B7*Assumptions!$C$29,0))) -> -117750 | C14: =IF(C$12=0,-Assumptions!$C$12*$B7*(1+SUM(Assumptions!$C$13:$C$17)),IF(C$12>$C7,0,(Assumptions!$C$25*Assumptions!$C$26*Assumptions!$C$20-Assumptions!$C$18-Assumptions!$C$19*Assumptions!$C$20*Assumptions!$C$21-Assumptions!$C$12*$B7*Assumptions!$C$22-Assumptions!$C$25*Assumptions!$C$26*Assumptions!$C$20*Assumptions!$C$27-Assumptions!$C$25*Assumptions!$C$26*Assumptions!$C$20*Assumptions!$C$28)*(1+Assumptions!$C$7)^(C$12-1)+IF(C$12=$C7,Assumptions!$C$12*$B7*Assumptions!$C$29,0))) -> 153611.33 | D14: =IF(D$12=0,-Assumptions!$C$12*$B7*(1+SUM(Assumptions!$C$13:$C$17)),IF(D$12>$C7,0,(Assumptions!$C$25*Assumptions!$C$26*Assumptions!$C$20-Assumptions!$C$18-Assumptions!$C$19*Assumptions!$C$20*Assumptions!$C$21-Assumptions!$C$12*$B7*Assumptions!$C$22-Assumptions!$C$25*Assumptions!$C$26*Assumptions!$C$20*Assumptions!$C$27-Assumptions!$C$25*Assumptions!$C$26*Assumptions!$C$20*Assumptions!$C$28)*(1+Assumptions!$C$7)^(D$12-1)+IF(D$12=$C7,Assumptions!$C$12*$B7*Assumptions!$C$29,0))) -> 158219.67 | E14: =IF(E$12=0,-Assumptions!$C$12*$B7*(1+SUM(Assumptions!$C$13:$C$17)),IF(E$12>$C7,0,(Assumptions!$C$25*Assumptions!$C$26*Assumptions!$C$20-Assumptions!$C$18-Assumptions!$C$19*Assumptions!$C$20*Assumptions!$C$21-Assumptions!$C$12*$B7*Assumptions!$C$22-Assumptions!$C$25*Assumptions!$C$26*Assumptions!$C$20*Assumptions!$C$27-Assumptions!$C$25*Assumptions!$C$26*Assumptions!$C$20*Assumptions!$C$28)*(1+Assumptions!$C$7)^(E$12-1)+IF(E$12=$C7,Assumptions!$C$12*$B7*Assumptions!$C$29,0))) -> 162966.26 | F14: =IF(F$12=0,-Assumptions!$C$12*$B7*(1+SUM(Assumptions!$C$13:$C$17)),IF(F$12>$C7,0,(Assumptions!$C$25*Assumptions!$C$26*Assumptions!$C$20-Assumptions!$C$18-Assumptions!$C$19*Assumptions!$C$20*Assumptions!$C$21-Assumptions!$C$12*$B7*Assumptions!$C$22-Assumptions!$C$25*Assumptions!$C$26*Assumptions!$C$20*Assumptions!$C$27-Assumptions!$C$25*Assumptions!$C$26*Assumptions!$C$20*Assumptions!$C$28)*(1+Assumptions!$C$7)^(F$12-1)+IF(F$12=$C7,Assumptions!$C$12*$B7*Assumptions!$C$29,0))) -> 167855.25 | G14: =IF(G$12=0,-Assumptions!$C$12*$B7*(1+SUM(Assumptions!$C$13:$C$17)),IF(G$12>$C7,0,(Assumptions!$C$25*Assumptions!$C$26*Assumptions!$C$20-Assumptions!$C$18-Assumptions!$C$19*Assumptions!$C$20*Assumptions!$C$21-Assumptions!$C$12*$B7*Assumptions!$C$22-Assumptions!$C$25*Assumptions!$C$26*Assumptions!$C$20*Assumptions!$C$27-Assumptions!$C$25*Assumptions!$C$26*Assumptions!$C$20*Assumptions!$C$28)*(1+Assumptions!$C$7)^(G$12-1)+IF(G$12=$C7,Assumptions!$C$12*$B7*Assumptions!$C$29,0))) -> 180390.91
A15: =A8 -> Useful life reduced to 3 years | B15: =IF(B$12=0,-Assumptions!$C$12*$B8*(1+SUM(Assumptions!$C$13:$C$17)),IF(B$12>$C8,0,(Assumptions!$C$25*Assumptions!$C$26*Assumptions!$C$20-Assumptions!$C$18-Assumptions!$C$19*Assumptions!$C$20*Assumptions!$C$21-Assumptions!$C$12*$B8*Assumptions!$C$22-Assumptions!$C$25*Assumptions!$C$26*Assumptions!$C$20*Assumptions!$C$27-Assumptions!$C$25*Assumptions!$C$26*Assumptions!$C$20*Assumptions!$C$28)*(1+Assumptions!$C$7)^(B$12-1)+IF(B$12=$C8,Assumptions!$C$12*$B8*Assumptions!$C$29,0))) -> -98125 | C15: =IF(C$12=0,-Assumptions!$C$12*$B8*(1+SUM(Assumptions!$C$13:$C$17)),IF(C$12>$C8,0,(Assumptions!$C$25*Assumptions!$C$26*Assumptions!$C$20-Assumptions!$C$18-Assumptions!$C$19*Assumptions!$C$20*Assumptions!$C$21-Assumptions!$C$12*$B8*Assumptions!$C$22-Assumptions!$C$25*Assumptions!$C$26*Assumptions!$C$20*Assumptions!$C$27-Assumptions!$C$25*Assumptions!$C$26*Assumptions!$C$20*Assumptions!$C$28)*(1+Assumptions!$C$7)^(C$12-1)+IF(C$12=$C8,Assumptions!$C$12*$B8*Assumptions!$C$29,0))) -> 154236.33 | D15: =IF(D$12=0,-Assumptions!$C$12*$B8*(1+SUM(Assumptions!$C$13:$C$17)),IF(D$12>$C8,0,(Assumptions!$C$25*Assumptions!$C$26*Assumptions!$C$20-Assumptions!$C$18-Assumptions!$C$19*Assumptions!$C$20*Assumptions!$C$21-Assumptions!$C$12*$B8*Assumptions!$C$22-Assumptions!$C$25*Assumptions!$C$26*Assumptions!$C$20*Assumptions!$C$27-Assumptions!$C$25*Assumptions!$C$26*Assumptions!$C$20*Assumptions!$C$28)*(1+Assumptions!$C$7)^(D$12-1)+IF(D$12=$C8,Assumptions!$C$12*$B8*Assumptions!$C$29,0))) -> 158863.42 | E15: =IF(E$12=0,-Assumptions!$C$12*$B8*(1+SUM(Assumptions!$C$13:$C$17)),IF(E$12>$C8,0,(Assumptions!$C$25*Assumptions!$C$26*Assumptions!$C$20-Assumptions!$C$18-Assumptions!$C$19*Assumptions!$C$20*Assumptions!$C$21-Assumptions!$C$12*$B8*Assumptions!$C$22-Assumptions!$C$25*Assumptions!$C$26*Assumptions!$C$20*Assumptions!$C$27-Assumptions!$C$25*Assumptions!$C$26*Assumptions!$C$20*Assumptions!$C$28)*(1+Assumptions!$C$7)^(E$12-1)+IF(E$12=$C8,Assumptions!$C$12*$B8*Assumptions!$C$29,0))) -> 169879.32 | F15: =IF(F$12=0,-Assumptions!$C$12*$B8*(1+SUM(Assumptions!$C$13:$C$17)),IF(F$12>$C8,0,(Assumptions!$C$25*Assumptions!$C$26*Assumptions!$C$20-Assumptions!$C$18-Assumptions!$C$19*Assumptions!$C$20*Assumptions!$C$21-Assumptions!$C$12*$B8*Assumptions!$C$22-Assumptions!$C$25*Assumptions!$C$26*Assumptions!$C$20*Assumptions!$C$27-Assumptions!$C$25*Assumptions!$C$26*Assumptions!$C$20*Assumptions!$C$28)*(1+Assumptions!$C$7)^(F$12-1)+IF(F$12=$C8,Assumptions!$C$12*$B8*Assumptions!$C$29,0))) -> 0 | G15: =IF(G$12=0,-Assumptions!$C$12*$B8*(1+SUM(Assumptions!$C$13:$C$17)),IF(G$12>$C8,0,(Assumptions!$C$25*Assumptions!$C$26*Assumptions!$C$20-Assumptions!$C$18-Assumptions!$C$19*Assumptions!$C$20*Assumptions!$C$21-Assumptions!$C$12*$B8*Assumptions!$C$22-Assumptions!$C$25*Assumptions!$C$26*Assumptions!$C$20*Assumptions!$C$27-Assumptions!$C$25*Assumptions!$C$26*Assumptions!$C$20*Assumptions!$C$28)*(1+Assumptions!$C$7)^(G$12-1)+IF(G$12=$C8,Assumptions!$C$12*$B8*Assumptions!$C$29,0))) -> 0
A18: Main result
A19: Largest NPV impact | B19: =IF(ABS(F7)>=ABS(F8),A7,A8) -> Useful life reduced to 3 years
A20: NPV reduction | B20: =MAX(ABS(F7),ABS(F8)) -> 243863.85
A21: Interpretation | B21: Shortening useful life to three years removes the final two years of savings and has the larger NPV impact in the current model.

Sheet Checks
A1: W04 Sentinel Prime AI Cost-Benefit Analysis — Checks
A5: Check | B5: Actual | C5: Expected | D5: Difference | E5: Tolerance | F5: Status | G5: Notes
A6: Initial investment components tie | B6: =ABS('Cash Flow'!B12) -> 98125 | C6: =Assumptions!C31 -> 98125 | D6: =B6-C6 -> 0 | E6: 0.01 | F6: =IF(ABS(D6)<=E6,"PASS","FAIL") -> PASS | G6: Initial investment is recognized once in Year 0.
A7: Discount rate equals Treasury plus risk premium | B7: =Assumptions!C10 -> 0.0775 | C7: =Assumptions!C8+Assumptions!C9 -> 0.0775 | D7: =B7-C7 -> 0 | E7: 1e-06 | F7: =IF(ABS(D7)<=E7,"PASS","FAIL") -> PASS | G7: 4.75% Treasury yield plus 3.00% risk premium.
A8: Base NPV ties to discounted cash flow | B8: ='Cash Flow'!B29 -> 561510.68 | C8: =SUM('Cash Flow'!B24:G24) -> 561510.68 | D8: =B8-C8 -> 0 | E8: 0.01 | F8: =IF(ABS(D8)<=E8,"PASS","FAIL") -> PASS | G8: NPV() result equals the displayed discounted cash-flow schedule.
A9: Base cash-flow sign pattern | B9: =COUNTIF('Cash Flow'!B22:G22,"<0")&"/"&COUNTIF('Cash Flow'!B22:G22,">0") -> 1/5 | C9: ="1/"&Assumptions!$C$6 -> 1/5 | F9: =IF(B9=C9,"PASS","FAIL") -> PASS | G9: One negative Year 0 flow and one positive flow for each active year.
A10: Nominal cash flow ties to W03 five-year savings | B10: =SUM('Cash Flow'!B22:G22) -> 726986.63 | C10: =Assumptions!C30 -> 726986.63 | D10: =B10-C10 -> 2.0954758e-09 | E10: 0.01 | F10: =IF(Assumptions!$C$6<>5,"N/A",IF(ABS(D10)<=E10,"PASS","FAIL")) -> PASS | G10: Ties to the W03 result when the selected horizon is five years.
A11: Three-year case has no Year 4–5 cash flow | B11: =ABS(Sensitivity!F15)+ABS(Sensitivity!G15) -> 0 | C11: 0 | D11: =B11-C11 -> 0 | E11: 0.01 | F11: =IF(ABS(D11)<=E11,"PASS","FAIL") -> PASS | G11: Useful-life sensitivity excludes Years 4 and 5.
A12: All required cases have positive NPV | B12: =COUNTIF(Sensitivity!E6:E8,">0") -> 3 | C12: 3 | D12: =B12-C12 -> 0 | E12: 0 | F12: =IF(D12=0,"PASS","FAIL") -> PASS | G12: Base and both required downside cases remain above zero.
A13: Sensitivity base cash flow ties to Cash Flow | B13: =ABS(Sensitivity!B13-'Cash Flow'!B22)+ABS(Sensitivity!C13-'Cash Flow'!C22)+ABS(Sensitivity!D13-'Cash Flow'!D22)+ABS(Sensitivity!E13-'Cash Flow'!E22)+ABS(Sensitivity!F13-'Cash Flow'!F22)+ABS(Sensitivity!G13-'Cash Flow'!G22) -> 0 | C13: 0 | D13: =B13-C13 -> 0 | E13: 0.01 | F13: =IF(ABS(D13)<=E13,"PASS","FAIL") -> PASS | G13: Independent scenario formulas match the base cash-flow schedule.
A15: MODEL STATUS | F15: =IF(COUNTIF(F6:F13,"FAIL")=0,"PASS","FAIL") -> PASS

Sheet Sources
A1: W04 Sentinel Prime AI Cost-Benefit Analysis — Sources
A5: Source ID | B5: Model Input / Use | C5: Value / Unit | D5: Period | E5: Source | F5: URL | G5: Notes
A6: S01 | B6: Sentinel baseline inputs and TCO reconciliation | C6: $98,125 initial investment; $726,987 nominal five-year savings | D6: Week 3 | E6: W03_TCO_Analysis.xlsx | G6: Provides the Sentinel cost structure, recurring costs, and W03 reconciliation value.
A7: S02 | B7: 10-year Treasury yield | C7: 4.75% | D7: 2026-07-31 | E7: U.S. Department of the Treasury — Daily Treasury Par Yield Curve Rates | F7: https://home.treasury.gov/resource-center/data-chart-center/interest-rates/TextView?field_tdr_date_value=2026&type=daily_treasury_yield_curve | G7: 10-year par yield used as the risk-free base rate.
A8: S03 | B8: Security-guard wage and benefit load | C8: $20.42/hour mean wage; 1.302 benefit factor | D8: May 2025 / March 2026 | E8: BLS OEWS and Employer Costs for Employee Compensation | F8: https://www.bls.gov/oes/tables.htm | G8: W04 separates the $20.42 mean wage and 1.302 benefit factor, then calculates loaded labor cost by formula.
A9: S04 | B9: Commercial electricity price | C9: $0.1341/kWh | D9: 2025 | E9: U.S. EIA Table 5.3 | F9: https://www.eia.gov/electricity/monthly/xls/table_5_03.xlsx | G9: U.S. commercial-sector annual average used in W03.
A10: S05 | B10: Sentinel cost tier and product role | C10: $25,000–$100,000 Tier 3 | D10: 2026-07-13 | E10: W01_InGen_BA_Landscape.md / InGen Dynamics | F10: https://ingendynamics.com/sentinel.html | G10: W03 uses the tier midpoint as the hardware/system estimate.
A11: S06 | B11: Discount-rate rule and required sensitivity cases | C11: 10-year Treasury + 3%; hardware +20%; life = 3 years | D11: Week 4 | E11: Internship plan | G11: Defines the W04 analysis method and required tests.
