Workbook

Sheet Overview
A1: W03 TAM / SAM / SOM Model — U.S. Market
A4: Market sizing summary | I4: Three-year SOM revenue
A5: Platform | B5: Layer | C5: Addressable units | D5: Unit definition | E5: Value per unit | F5: Revenue opportunity | G5: Main filter | I5: Platform | J5: Revenue
A6: Fari | B6: TAM | C6: =Fari!B6 -> 14695 | D6: nursing facilities | E6: =Fari!D6 -> 15000 | F6: =Fari!E6 -> 220425000 | G6: All CMS providers | I6: Fari | J6: =F8 -> 1110000
A7: Fari | B7: SAM | C7: =Fari!B7 -> 7395 | D7: nursing facilities | E7: =Fari!D7 -> 15000 | F7: =Fari!E7 -> 110925000 | G7: Certified beds >= 100 | I7: Senpai | J7: =F11 -> 2395590
A8: Fari | B8: SOM | C8: =Fari!B8 -> 74 | D8: nursing facilities | E8: =Fari!D8 -> 15000 | F8: =Fari!E8 -> 1110000 | G8: SAM × 1.0% | I8: Sentinel Prime AI | J8: =F14 -> 17250000
A9: Senpai | B9: TAM | C9: =Senpai!B6 -> 100237 | D9: public schools | E9: =Senpai!D6 -> 16990 | F9: =Senpai!E6 -> 1703026630 | G9: Active schools
A10: Senpai | B10: SAM | C10: =Senpai!B7 -> 28218 | D10: public schools | E10: =Senpai!D7 -> 16990 | F10: =Senpai!E7 -> 479423820 | G10: Regular K–8-serving schools, enrollment >= 500
A11: Senpai | B11: SOM | C11: =Senpai!B8 -> 141 | D11: public schools | E11: =Senpai!D8 -> 16990 | F11: =Senpai!E8 -> 2395590 | G11: SAM × 0.5%
A12: Sentinel Prime AI | B12: TAM | C12: =Sentinel!B6 -> 1283470 | D12: deployments | E12: =Sentinel!E6 -> 62500 | F12: =Sentinel!F6 -> 80216875000 | G12: All U.S. security guard FTE
A13: Sentinel Prime AI | B13: SAM | C13: =Sentinel!B7 -> 919750 | D13: deployments | E13: =Sentinel!E7 -> 62500 | F13: =Sentinel!F7 -> 57484375000 | G13: Selected target industries
A14: Sentinel Prime AI | B14: SOM | C14: =Sentinel!B8 -> 276 | D14: deployments | E14: =Sentinel!E8 -> 62500 | F14: =Sentinel!F8 -> 17250000 | G14: SAM × 0.03% base case

Sheet Assumptions
A1: W03 TAM / SAM / SOM Model — Assumptions
A3: Light gray value cells are editable estimates. Public-source facts remain white. Revenue outputs are illustrative, not InGen quotations.
A5: Platform | B5: Input | C5: Value | D5: Unit | E5: Type | F5: Source ID | G5: Derivation / Note
A6: Fari | B6: TAM certified facilities | C6: 14695 | D6: facilities | E6: Public source | F6: S01 | G6: All rows in CMS Provider Information
A7: Fari | B7: TAM certified beds | C7: 1568348 | D7: beds | E7: Public source | F7: S01 | G7: Sum of Number of Certified Beds
A8: Fari | B8: TAM average residents per day | C8: 1247194.4 | D8: residents/day | E8: Public source | F8: S01 | G8: Sum of Average Number of Residents per Day
A9: Fari | B9: SAM facilities | C9: 7395 | D9: facilities | E9: Derived from source | F9: S01 | G9: Certified beds >= 100
A10: Fari | B10: SAM certified beds | C10: 1086260 | D10: beds | E10: Derived from source | F10: S01 | G10: Beds within facilities having >= 100 certified beds
A11: Fari | B11: SAM average residents per day | C11: 854862 | D11: residents/day | E11: Derived from source | F11: S01 | G11: Residents within facilities having >= 100 certified beds
A12: Fari | B12: Three-year SOM capture | C12: 0.01 | D12: % of SAM | E12: Analyst estimate | F12: S11 | G12: Early U.S. penetration assumption for an in-development product
A13: Fari | B13: Estimated first-year revenue per site | C13: =AVERAGE(C14:C15) -> 15000 | D13: USD/site | E13: Formula | F13: S08 | G13: Midpoint of the Week 1 Tier 2 range
A14: Fari | B14: Tier 2 lower bound | C14: 5000 | D14: USD/site | E14: Analyst estimate | F14: S08 | G14: Week 1 cost-tier boundary
A15: Fari | B15: Tier 2 upper bound | C15: 25000 | D15: USD/site | E15: Analyst estimate | F15: S08 | G15: Week 1 cost-tier boundary
A16: Senpai | B16: TAM active public schools | C16: 100237 | D16: schools | E16: Derived from source | F16: S02/S03 | G16: Status codes 1, 3, 4, 5, and 8
A17: Senpai | B17: TAM students | C17: 49342639 | D17: students | E17: Derived from source | F17: S03 | G17: Students in active schools
A18: Senpai | B18: SAM schools | C18: 28218 | D18: schools | E18: Derived from source | F18: S02/S03 | G18: Active regular schools, K–8 enrollment > 0, total enrollment >= 500
A19: Senpai | B19: SAM students | C19: 21040790 | D19: students | E19: Derived from source | F19: S03 | G19: Total students in selected SAM schools
A20: Senpai | B20: SAM K–8 students | C20: 19314776 | D20: students | E20: Derived from source | F20: S03 | G20: K–8 students in selected SAM schools
A21: Senpai | B21: Three-year SOM capture | C21: 0.005 | D21: % of SAM | E21: Analyst estimate | F21: S11 | G21: Conservative school procurement assumption
A22: Senpai | B22: Estimated first-year revenue per school | C22: 16990 | D22: USD/school | E22: Public analogue | F22: S04 | G22: NAO V6 public institutional price
A23: Senpai | B23: Units per school | C23: 1 | D23: unit/school | E23: Analyst estimate | F23: S11 | G23: One Senpai deployment per school
A24: Senpai | B24: NCES valid school rows | C24: 101110 | D24: schools | E24: Derived from source | F24: S02 | G24: Rows with a 12-digit NCES school ID
A25: Senpai | B25: Inactive schools excluded | C25: 501 | D25: schools | E25: Public source | F25: S02 | G25: Status 6-Inactive
... A29: Sentinel | B29: Mean annual guard wage | C29: 42470 | D29: USD/FTE/year | E29: Public source | F29: S05 | G29: A_MEAN for OCC 33-9032
A30: Sentinel | B30: TAM annual wage pool | C30: =C28*C29 -> 54508970900 | D30: USD/year | E30: Formula | F30: S05 | G30: Guard FTE multiplied by mean annual wage
A31: Sentinel | B31: SAM target-industry guard FTE | C31: 919750 | D31: guard FTE | E31: Derived from source | F31: S06 | G31: Selected 4-digit NAICS industries; includes contract security as a channel/operator market
A32: Sentinel | B32: SAM annual wage pool | C32: 39074694700 | D32: USD/year | E32: Derived from source | F32: S06 | G32: Sum of employment multiplied by mean annual wage
A33: Sentinel | B33: Three-year SOM capture — Low | C33: 0.0002 | D33: % of SAM | E33: Analyst estimate | F33: S11 | G33: Low early-market case
A34: Sentinel | B34: Three-year SOM capture — Base | C34: 0.0003 | D34: % of SAM | E34: Analyst estimate | F34: S11 | G34: Base case used in the market model
A35: Sentinel | B35: Three-year SOM capture — High | C35: 0.001 | D35: % of SAM | E35: Analyst estimate | F35: S11 | G35: Prior 0.1% case retained as an upside test
A36: Sentinel | B36: IFR security/search/rescue units | C36: 3128 | D36: units/year | E36: Public source | F36: S09 | G36: 2024 global supplier sample; directional comparison only
A37: Sentinel | B37: IFR security-use share | C37: 0.75 | D37: % of category | E37: Derived from source | F37: S09 | G37: IFR states that about three quarters were for security services
A38: Sentinel | B38: IFR security-use units | C38: =C36*C37 -> 2346 | D38: units/year | E38: Formula | F38: S09 | G38: Security/search/rescue units multiplied by security-use share
A39: Sentinel | B39: Estimated hardware/system value | C39: 62500 | D39: USD/deployment | E39: Analyst estimate | F39: S07/S08 | G39: One-time system estimate; Knightscope reports annual service revenue, so the units differ
A40: Sentinel | B40: Guard FTE addressed per deployment | C40: 1 | D40: guard FTE/deployment | E40: Analyst estimate | F40: S11 | G40: Sizing convention; does not claim full labor replacement

Sheet Fari
A1: Fari — U.S. TAM / SAM / SOM
A5: Layer | B5: Addressable facilities | C5: Supporting residents/day | D5: First-year value/site | E5: Revenue opportunity | F5: Rule
A6: TAM | B6: =Assumptions!C6 -> 14695 | C6: =Assumptions!C8 -> 1247194.4 | D6: =Assumptions!C13 -> 15000 | E6: =B6*D6 -> 220425000 | F6: All CMS-certified nursing facilities
A7: SAM | B7: =Assumptions!C9 -> 7395 | C7: =Assumptions!C11 -> 854862 | D7: =Assumptions!C13 -> 15000 | E7: =B7*D7 -> 110925000 | F7: Facilities with at least 100 certified beds
A8: SOM | B8: =ROUND(Assumptions!C9*Assumptions!C12,0) -> 74 | C8: =ROUND(Assumptions!C11*Assumptions!C12,0) -> 8549 | D8: =Assumptions!C13 -> 15000 | E8: =B8*D8 -> 1110000 | F8: SAM × three-year capture rate
A10: Logic and interpretation
A11: Logic | B11: Basis | C11: Threshold / Rate | D11: Interpretation
A12: TAM logic | B12: Facility count | C12: CMS provider rows | D12: Represents the broad U.S. institutional universe.
A13: SAM logic | B13: Facility size | C13: >= 100 certified beds | D13: Larger facilities have a stronger potential budget and more residents per deployment.
A14: SOM logic | B14: Three-year capture | C14: =Assumptions!C12 -> 0.01 | D14: A 1.0% share of SAM is an editable early-market assumption.

Sheet Senpai
A1: Senpai — U.S. TAM / SAM / SOM
A5: Layer | B5: Addressable schools | C5: Student enrollment | D5: Assumed value per school | E5: Revenue opportunity | F5: Definition
A6: TAM | B6: =Assumptions!C16 -> 100237 | C6: =Assumptions!C17 -> 49342639 | D6: =Assumptions!C22 -> 16990 | E6: =B6*D6 -> 1703026630 | F6: Active public schools with NCES status codes 1, 3, 4, 5, or 8
A7: SAM | B7: =Assumptions!C18 -> 28218 | C7: =Assumptions!C19 -> 21040790 | D7: =Assumptions!C22 -> 16990 | E7: =B7*D7 -> 479423820 | F7: Active regular schools with K–8 enrollment above 0 and total enrollment of at least 500
A8: SOM | B8: =ROUND(Assumptions!C18*Assumptions!C21,0) -> 141 | C8: =ROUND(Assumptions!C19*Assumptions!C21,0) -> 105204 | D8: =Assumptions!C22 -> 16990 | E8: =B8*D8 -> 2395590 | F8: 0.5% of SAM over three years, rounded to 141 schools

Sheet Sentinel
A1: Sentinel Prime AI — U.S. TAM / SAM / SOM
A2: Unit of analysis: one deployment opportunity per guard FTE.
A5: Layer | B5: Deployment opportunities | C5: Guard FTE basis | D5: Annual wage pool | E5: Value per deployment | F5: Estimated market value | G5: Definition
A6: TAM | B6: =Assumptions!C28/Assumptions!C40 -> 1283470 | C6: =Assumptions!C28 -> 1283470 | D6: =Assumptions!C30 -> 54508970900 | E6: =Assumptions!C39 -> 62500 | F6: =B6*E6 -> 80216875000 | G6: All U.S. Security Guards (OCC 33-9032)
A7: SAM | B7: =Assumptions!C31/Assumptions!C40 -> 919750 | C7: =Assumptions!C31 -> 919750 | D7: =Assumptions!C32 -> 39074694700 | E7: =Assumptions!C39 -> 62500 | F7: =B7*E7 -> 57484375000 | G7: Selected NAICS target industries listed below
A8: SOM | B8: =ROUND(B7*Assumptions!C34,0) -> 276 | C8: =B8*Assumptions!C40 -> 276 | D8: =Assumptions!C32*Assumptions!C34 -> 11722408 | E8: =Assumptions!C39 -> 62500 | F8: =B8*E8 -> 17250000 | G8: 0.03% of SAM over three years, rounded to 276 deployments
A11: SAM target industries — BLS OEWS May 2025
A12: NAICS | B12: Industry | C12: Security guard FTE | D12: Mean hourly wage | E12: Mean annual wage | F12: Annual wage pool | G12: Source ID
A13: 221100 | B13: Electric Power Generation, Transmission and Distribution | C13: 4610 | D13: 32.9 | E13: 68440 | F13: =C13*E13 -> 315508400 | G13: S06
A14: 221200 | B14: Natural Gas Distribution | C14: 70 | D14: 44.01 | E14: 91540 | F14: =C14*E14 -> 6407800 | G14: S06
A15: 221300 | B15: Water, Sewage and Other Systems | C15: 70 | D15: 18.31 | E15: 38080 | F15: =C15*E15 -> 2665600 | G15: S06
A16: 493100 | B16: Warehousing and Storage | C16: 7270 | D16: 23.07 | E16: 47980 | F16: =C16*E16 -> 348814600 | G16: S06
A17: 531000 | B17: Real Estate | C17: 25700 | D17: 23.87 | E17: 49640 | F17: =C17*E17 -> 1275748000 | G17: S06
A18: 561600 | B18: Investigation and Security Services | C18: 768900 | D18: 19.9 | E18: 41380 | F18: =C18*E18 -> 31817082000 | G18: S06
A19: 611100 | B19: Elementary and Secondary Schools | C19: 58300 | D19: 22.32 | E19: 46430 | F19: =C19*E19 -> 2706869000 | G19: S06
A20: 622100 | B20: General Medical and Surgical Hospitals | C20: 49340 | D20: 22.76 | E20: 47350 | F20: =C20*E20 -> 2336249000 | G20: S06
A21: 622200 | B21: Psychiatric and Substance Abuse Hospitals | C21: 4150 | D21: 23.26 | E21: 48370 | F21: =C21*E21 -> 200735500 | G21: S06
A22: 622300 | B22: Specialty (except Psychiatric and Substance Abuse) Hospitals | C22: 1340 | D22: 23.18 | E22: 48220 | F22: =C22*E22 -> 64614800 | G22: S06
A23: SAM total | C23: =SUM(C13:C22) -> 919750 | F23: =SUM(F13:F22) -> 39074694700 | G23: S06
A26: SAM interpretation
A27: Metric | B27: Value | C27: Unit | D27: Explanation
A28: Direct-site SAM excluding NAICS 561600 | B28: =C23-C18 -> 150850 | C28: guard FTE | D28: Customer-site industries only; excludes the contract-security channel pool.
A29: Direct-site annual wage pool | B29: =F23-F18 -> 7257612700 | C29: USD/year | D29: Annual wage pool for the direct-site industries above.
A30: Contract-security channel/operator pool | B30: =C18 -> 768900 | C30: guard FTE | D30: NAICS 561600 is included because security firms may buy and operate the system for client sites. This is an employer-side FTE pool, not a site count.
A31: Ownership coverage | B31: OWN_CODE 235 | C31: combined | D31: NAICS 611100 and 622100/622200/622300 combine private, state, and local government employment.

Sheet Checks
A1: W03 TAM / SAM / SOM Model — Checks
A5: Check | B5: Actual | C5: Expected | D5: Difference | E5: Tolerance | F5: Status | G5: Notes
A6: Fari hierarchy: TAM >= SAM | B6: =Fari!B6-Fari!B7 -> 7300 | C6: 0 | D6: =B6-C6 -> 7300 | E6: 0 | F6: =IF(B6>=0,"PASS","FAIL") -> PASS | G6: Facility count must narrow from TAM to SAM.
A7: Fari hierarchy: SAM >= SOM | B7: =Fari!B7-Fari!B8 -> 7321 | C7: 0 | D7: =B7-C7 -> 7321 | E7: 0 | F7: =IF(B7>=0,"PASS","FAIL") -> PASS | G7: SOM cannot exceed the targetable market.
A8: Senpai hierarchy: TAM >= SAM >= SOM | B8: =MIN(Senpai!B6-Senpai!B7,Senpai!B7-Senpai!B8) -> 28077 | C8: 0 | D8: =B8-C8 -> 28077 | E8: 0 | F8: =IF(B8>=0,"PASS","FAIL") -> PASS | G8: Both narrowing steps must be non-negative.
A9: NCES population reconciliation | B9: =SUM(Assumptions!C16,Assumptions!C25,Assumptions!C26) -> 101110 | C9: =Assumptions!C24 -> 101110 | D9: =B9-C9 -> 0 | E9: 0 | F9: =IF(ABS(D9)<=E9,"PASS","FAIL") -> PASS | G9: Active + inactive + future schools equals valid source rows.
A10: Sentinel industry FTE ties to SAM | B10: =Sentinel!C23 -> 919750 | C10: =Assumptions!C31 -> 919750 | D10: =B10-C10 -> 0 | E10: 0 | F10: =IF(ABS(D10)<=E10,"PASS","FAIL") -> PASS | G10: Selected 4-digit NAICS rows reconcile to the SAM input.
A11: Fari site value is midpoint of Tier 2 | B11: =Assumptions!C13 -> 15000 | C11: =AVERAGE(Assumptions!C14:'Assumptions'!C15) -> 15000 | D11: =B11-C11 -> 0 | E11: 0 | F11: =IF(ABS(D11)<=E11,"PASS","FAIL") -> PASS | G11: Midpoint = ($5,000 + $25,000) / 2.
A12: Sentinel annualized SOM vs. IFR security-use units | B12: =(Sentinel!B8/3)/Assumptions!C38 -> 0.039215686 | C12: 0.05 | D12: =B12-C12 -> -0.010784314 | E12: 0 | F12: =IF(B12<=C12,"PASS","FAIL") -> PASS | G12: Directional screen: annualized U.S. base SOM stays below 5% of IFR's approximate 2024 global security-use units.
A16: MODEL STATUS | F16: =IF(COUNTIF(F6:F12,"FAIL")=0,"PASS","FAIL") -> PASS

Sheet Sources
A1: Sources
A5: Source ID | B5: Model Input / Use | C5: Value / Unit | D5: Period | E5: Source | F5: URL | G5: Notes
A6: S01 | B6: Fari facility, bed, and resident counts | C6: 14,695 facilities | D6: 2026-06-01 | E6: CMS Provider Information | F6: https://data.cms.gov/provider-data/dataset/4pq5-n9py | G6: SAM filter: certified beds ≥100.
A7: S02 | B7: Senpai school status and school type | C7: 101,110 valid schools | D7: 2024–25 v2a | E7: NCES ELSi Public School Directory | F7: https://nces.ed.gov/ccd/elsi/ | G7: TAM excludes inactive and future schools.
A8: S03 | B8: Senpai enrollment and K–8 counts | C8: 49,342,639 active-school students | D8: 2024–25 | E8: NCES ELSi Student Enrollment | F8: https://nces.ed.gov/ccd/elsi/ | G8: Enrollment unavailable for 992 active schools.
A9: S04 | B9: Senpai first-year value analogue | C9: $16,990 per unit | D9: Current listing used in Week 1 | E9: RobotLAB NAO V6 Standard Edition | F9: https://www.robotlab.com/store/nao-v6-standard-edition/
A10: S05 | B10: Sentinel national security-guard employment and wage | C10: 1,283,470 FTE; $42,470/year | D10: May 2025 | E10: BLS OEWS National | F10: https://www.bls.gov/oes/tables.htm
A11: S06 | B11: Sentinel target-industry employment and wages | C11: 919,750 guard FTE | D11: May 2025 | E11: BLS OEWS National Industry-Specific | F11: https://www.bls.gov/oes/tables.htm | G11: NAICS 561600 is a channel/operator pool; OWN_CODE 235 combines private, state, and local employment.
A12: S07 | B12: Sentinel price reasonableness anchor | C12: $42,000–$97,800/year | D12: 2021 filing | E12: Knightscope SEC filing | F12: https://www.sec.gov/Archives/edgar/data/1600983/000110465921059135/tm2113857d1_partii.htm | G12: Annual MaaS benchmark; the model uses a one-time system estimate.
A13: S08 | B13: Fari and Sentinel estimated price tiers | C13: Tier 2 / Tier 3 | D13: 2026-07-13 | E13: W01_InGen_BA_Landscape.md | F13: https://www.ingendynamics.com/
A14: S09 | B14: Service-robot market context | C14: 3,128 security/search/rescue units; about 75% for security | D14: 2024 results | E14: IFR World Robotics 2025 Executive Summary | F14: https://ifr.org/img/worldrobotics/Executive_Summary_WR_2025_Service_Robots.pdf | G14: Directional global check only; not the U.S. market denominator.
A15: S10 | B15: Ageing-demand context for Fari | C15: Global population aged 60+ trend | D15: 2020–2050 | E15: WHO Ageing and Health | F15: https://www.who.int/news-room/fact-sheets/detail/ageing-and-health
A16: S11 | B16: Capture rates and one-unit conventions | C16: Low / Base / High estimates | D16: Three-year model | E16: Analyst assumptions | G16: Low/Base/High capture: 0.02% / 0.03% / 0.10%.
